{
"meta":{"test_sets":[],"test_metrics":[],"learn_metrics":[{"best_value":"Min","name":"RMSE"}],"launch_mode":"Train","parameters":"","iteration_count":200,"learn_sets":["learn"],"name":"experiment"},
"iterations":[
{"learn":[0.9831351166],"iteration":0,"passed_time":0.008189131962,"remaining_time":1.62963726},
{"learn":[0.9752112564],"iteration":1,"passed_time":0.01596090237,"remaining_time":1.580129335},
{"learn":[0.9681708168],"iteration":2,"passed_time":0.02316386981,"remaining_time":1.521094118},
{"learn":[0.9641019793],"iteration":3,"passed_time":0.0267095477,"remaining_time":1.308767837},
{"learn":[0.9605952109],"iteration":4,"passed_time":0.02996449821,"remaining_time":1.16861543},
{"learn":[0.9567301853],"iteration":5,"passed_time":0.03777290952,"remaining_time":1.221324074},
{"learn":[0.952415837],"iteration":6,"passed_time":0.04518182067,"remaining_time":1.245727341},
{"learn":[0.9486289126],"iteration":7,"passed_time":0.05260202734,"remaining_time":1.262448656},
{"learn":[0.9466649737],"iteration":8,"passed_time":0.05975581027,"remaining_time":1.268151085},
{"learn":[0.9442648916],"iteration":9,"passed_time":0.06687390678,"remaining_time":1.270604229},
{"learn":[0.9423433063],"iteration":10,"passed_time":0.07419982867,"remaining_time":1.274887965},
{"learn":[0.9397618627],"iteration":11,"passed_time":0.08132353385,"remaining_time":1.274068697},
{"learn":[0.9375043321],"iteration":12,"passed_time":0.08855507643,"remaining_time":1.273830715},
{"learn":[0.9359935327],"iteration":13,"passed_time":0.09596067782,"remaining_time":1.274906148},
{"learn":[0.9348810838],"iteration":14,"passed_time":0.103193603,"remaining_time":1.272721104},
{"learn":[0.9346666881],"iteration":15,"passed_time":0.1050407832,"remaining_time":1.207969007},
{"learn":[0.933177176],"iteration":16,"passed_time":0.11334796,"remaining_time":1.220157452},
{"learn":[0.9321322614],"iteration":17,"passed_time":0.1207065113,"remaining_time":1.220476947},
{"learn":[0.9306547195],"iteration":18,"passed_time":0.1281204284,"remaining_time":1.22051566},
{"learn":[0.9295184371],"iteration":19,"passed_time":0.1355133799,"remaining_time":1.219620419},
{"learn":[0.9282830958],"iteration":20,"passed_time":0.1431130104,"remaining_time":1.219868041},
{"learn":[0.9272508655],"iteration":21,"passed_time":0.1502602947,"remaining_time":1.215742385},
{"learn":[0.9261338693],"iteration":22,"passed_time":0.1573966417,"remaining_time":1.211269808},
{"learn":[0.9246457262],"iteration":23,"passed_time":0.1647945064,"remaining_time":1.208493047},
{"learn":[0.9237438584],"iteration":24,"passed_time":0.1721901958,"remaining_time":1.205331371},
{"learn":[0.9226378969],"iteration":25,"passed_time":0.1795837817,"remaining_time":1.201829924},
{"learn":[0.9218706789],"iteration":26,"passed_time":0.1875854159,"remaining_time":1.201936183},
{"learn":[0.9207438281],"iteration":27,"passed_time":0.1956367018,"remaining_time":1.201768311},
{"learn":[0.920025767],"iteration":28,"passed_time":0.2040613007,"remaining_time":1.203258014},
{"learn":[0.9193632972],"iteration":29,"passed_time":0.2118205484,"remaining_time":1.200316441},
{"learn":[0.9184329105],"iteration":30,"passed_time":0.2193400976,"remaining_time":1.195757307},
{"learn":[0.918137861],"iteration":31,"passed_time":0.2219421342,"remaining_time":1.165196205},
{"learn":[0.9174303229],"iteration":32,"passed_time":0.2299015088,"remaining_time":1.163440969},
{"learn":[0.9163092918],"iteration":33,"passed_time":0.2373087482,"remaining_time":1.158625065},
{"learn":[0.9157980956],"iteration":34,"passed_time":0.2443905756,"remaining_time":1.152126999},
{"learn":[0.9151216598],"iteration":35,"passed_time":0.2516465427,"remaining_time":1.146389806},
{"learn":[0.9145514983],"iteration":36,"passed_time":0.2585451793,"remaining_time":1.13899633},
{"learn":[0.9138722779],"iteration":37,"passed_time":0.2656248614,"remaining_time":1.132400725},
{"learn":[0.9132708421],"iteration":38,"passed_time":0.2730166429,"remaining_time":1.127068705},
{"learn":[0.9129056913],"iteration":39,"passed_time":0.2800825079,"remaining_time":1.120330031},
{"learn":[0.9123148499],"iteration":40,"passed_time":0.2871242673,"remaining_time":1.113481915},
{"learn":[0.9117274065],"iteration":41,"passed_time":0.2952883548,"remaining_time":1.110846668},
{"learn":[0.9110461654],"iteration":42,"passed_time":0.3024149916,"remaining_time":1.104166365},
{"learn":[0.9103384512],"iteration":43,"passed_time":0.309869812,"remaining_time":1.098629334},
{"learn":[0.9096471437],"iteration":44,"passed_time":0.3171758854,"remaining_time":1.092494716},
{"learn":[0.9095358668],"iteration":45,"passed_time":0.3222196105,"remaining_time":1.078735218},
{"learn":[0.9090605591],"iteration":46,"passed_time":0.3300434761,"remaining_time":1.074396848},
{"learn":[0.908005665],"iteration":47,"passed_time":0.33759768,"remaining_time":1.06905932},
{"learn":[0.9076946687],"iteration":48,"passed_time":0.3445082275,"remaining_time":1.061647803},
{"learn":[0.9071699188],"iteration":49,"passed_time":0.3518080504,"remaining_time":1.055424151},
{"learn":[0.907036145],"iteration":50,"passed_time":0.3588284915,"remaining_time":1.048342063},
{"learn":[0.9062913971],"iteration":51,"passed_time":0.3660307354,"remaining_time":1.041779785},
{"learn":[0.905799424],"iteration":52,"passed_time":0.3733511749,"remaining_time":1.035521183},
{"learn":[0.9049289894],"iteration":53,"passed_time":0.3809244484,"remaining_time":1.029906842},
{"learn":[0.9040739332],"iteration":54,"passed_time":0.3884937493,"remaining_time":1.024210794},
{"learn":[0.9038876484],"iteration":55,"passed_time":0.3952707831,"remaining_time":1.016410585},
{"learn":[0.9030688057],"iteration":56,"passed_time":0.4027074068,"remaining_time":1.010301038},
{"learn":[0.9029112603],"iteration":57,"passed_time":0.4093248698,"remaining_time":1.002140198},
{"learn":[0.9021790336],"iteration":58,"passed_time":0.416823047,"remaining_time":0.9961364343},
{"learn":[0.9017915401],"iteration":59,"passed_time":0.4238362159,"remaining_time":0.9889511703},
{"learn":[0.9013527617],"iteration":60,"passed_time":0.4309573885,"remaining_time":0.9820176557},
{"learn":[0.9012102699],"iteration":61,"passed_time":0.4378230439,"remaining_time":0.9745093557},
{"learn":[0.9009874741],"iteration":62,"passed_time":0.4445813191,"remaining_time":0.9667879478},
{"learn":[0.9003987207],"iteration":63,"passed_time":0.451586244,"remaining_time":0.9596207685},
{"learn":[0.9000699857],"iteration":64,"passed_time":0.4586241983,"remaining_time":0.9525271811},
{"learn":[0.8995815909],"iteration":65,"passed_time":0.4659739912,"remaining_time":0.9460684063},
{"learn":[0.8989910961],"iteration":66,"passed_time":0.4734061924,"remaining_time":0.9397466207},
{"learn":[0.8984700368],"iteration":67,"passed_time":0.4809061395,"remaining_time":0.9335236825},
{"learn":[0.8981892352],"iteration":68,"passed_time":0.4879237526,"remaining_time":0.926347994},
{"learn":[0.897898484],"iteration":69,"passed_time":0.4947709366,"remaining_time":0.9188603108},
{"learn":[0.8975283198],"iteration":70,"passed_time":0.5021176569,"remaining_time":0.9122982781},
{"learn":[0.8969072618],"iteration":71,"passed_time":0.513126611,"remaining_time":0.9122250862},
{"learn":[0.8960064272],"iteration":72,"passed_time":0.5232744512,"remaining_time":0.9103541822},
{"learn":[0.8953891463],"iteration":73,"passed_time":0.5333526602,"remaining_time":0.9081410161},
{"learn":[0.8951067855],"iteration":74,"passed_time":0.5456232246,"remaining_time":0.909372041},
{"learn":[0.8948767933],"iteration":75,"passed_time":0.5636957429,"remaining_time":0.9197141068},
{"learn":[0.894152732],"iteration":76,"passed_time":0.5711347582,"remaining_time":0.9123321462},
{"learn":[0.893459928],"iteration":77,"passed_time":0.5787986184,"remaining_time":0.9053004032},
{"learn":[0.8930278086],"iteration":78,"passed_time":0.5863455175,"remaining_time":0.8980735141},
{"learn":[0.8923888783],"iteration":79,"passed_time":0.5936084904,"remaining_time":0.8904127356},
{"learn":[0.8917448209],"iteration":80,"passed_time":0.6009784672,"remaining_time":0.8829189827},
{"learn":[0.8909868697],"iteration":81,"passed_time":0.6084602402,"remaining_time":0.8755891261},
{"learn":[0.8904776759],"iteration":82,"passed_time":0.6163694603,"remaining_time":0.8688581549},
{"learn":[0.8899839221],"iteration":83,"passed_time":0.6239251369,"remaining_time":0.8616109033},
{"learn":[0.8892983735],"iteration":84,"passed_time":0.6314333433,"remaining_time":0.8542921704},
{"learn":[0.889203553],"iteration":85,"passed_time":0.6349981616,"remaining_time":0.8417417491},
{"learn":[0.8889774685],"iteration":86,"passed_time":0.6424678728,"remaining_time":0.8344697658},
{"learn":[0.8886777163],"iteration":87,"passed_time":0.6496153853,"remaining_time":0.8267832176},
{"learn":[0.8881555937],"iteration":88,"passed_time":0.656898104,"remaining_time":0.8192774106},
{"learn":[0.8875994255],"iteration":89,"passed_time":0.6647007358,"remaining_time":0.8124120104},
{"learn":[0.8867939494],"iteration":90,"passed_time":0.6723698366,"remaining_time":0.805366068},
{"learn":[0.8862847851],"iteration":91,"passed_time":0.6794519703,"remaining_time":0.7976175304},
{"learn":[0.8860894746],"iteration":92,"passed_time":0.686404411,"remaining_time":0.7897341073},
{"learn":[0.8857712322],"iteration":93,"passed_time":0.6935661279,"remaining_time":0.7821064846},
{"learn":[0.8850928727],"iteration":94,"passed_time":0.7009906615,"remaining_time":0.7747791522},
{"learn":[0.8843592092],"iteration":95,"passed_time":0.708650153,"remaining_time":0.7677043324},
{"learn":[0.883925628],"iteration":96,"passed_time":0.7156854266,"remaining_time":0.7599546283},
{"learn":[0.8834390947],"iteration":97,"passed_time":0.7229940098,"remaining_time":0.7525039694},
{"learn":[0.8832373898],"iteration":98,"passed_time":0.7299956005,"remaining_time":0.7447429863},
{"learn":[0.8827036492],"iteration":99,"passed_time":0.7370089394,"remaining_time":0.7370089394},
{"learn":[0.8823059769],"iteration":100,"passed_time":0.7440220264,"remaining_time":0.729288917},
{"learn":[0.8814523324],"iteration":101,"passed_time":0.7514782077,"remaining_time":0.7220084741},
{"learn":[0.880778272],"iteration":102,"passed_time":0.761812194,"remaining_time":0.7174347846},
{"learn":[0.8801845243],"iteration":103,"passed_time":0.7701592096,"remaining_time":0.7109161935},
{"learn":[0.879632971],"iteration":104,"passed_time":0.7790800578,"remaining_time":0.7048819571},
{"learn":[0.8790356893],"iteration":105,"passed_time":0.7864121274,"remaining_time":0.6973843394},
{"learn":[0.8785122205],"iteration":106,"passed_time":0.793841628,"remaining_time":0.6899744991},
{"learn":[0.8776838562],"iteration":107,"passed_time":0.8014670984,"remaining_time":0.682731232},
{"learn":[0.8770795383],"iteration":108,"passed_time":0.8088416976,"remaining_time":0.675271509},
{"learn":[0.8765002828],"iteration":109,"passed_time":0.8159519783,"remaining_time":0.6675970731},
{"learn":[0.8763464762],"iteration":110,"passed_time":0.8227744405,"remaining_time":0.6597020289},
{"learn":[0.8758682415],"iteration":111,"passed_time":0.8297454907,"remaining_time":0.6519428856},
{"learn":[0.8755578315],"iteration":112,"passed_time":0.8367219287,"remaining_time":0.6442018389},
{"learn":[0.8752302709],"iteration":113,"passed_time":0.8435629205,"remaining_time":0.6363720277},
{"learn":[0.8750998968],"iteration":114,"passed_time":0.8503629398,"remaining_time":0.6285291294},
{"learn":[0.8744908242],"iteration":115,"passed_time":0.8577125818,"remaining_time":0.6211022144},
{"learn":[0.8737846153],"iteration":116,"passed_time":0.8653264149,"remaining_time":0.6138640379},
{"learn":[0.8729231208],"iteration":117,"passed_time":0.8728048972,"remaining_time":0.606525437},
{"learn":[0.8725169842],"iteration":118,"passed_time":0.880060917,"remaining_time":0.5990330612},
{"learn":[0.8718580551],"iteration":119,"passed_time":0.8875243396,"remaining_time":0.591682893},
{"learn":[0.8711890348],"iteration":120,"passed_time":0.8948199283,"remaining_time":0.5842212755},
{"learn":[0.8709619326],"iteration":121,"passed_time":0.9019662409,"remaining_time":0.5766669409},
{"learn":[0.8705316801],"iteration":122,"passed_time":0.9095066695,"remaining_time":0.5693659638},
{"learn":[0.8702147255],"iteration":123,"passed_time":0.9174375116,"remaining_time":0.5623004103},
{"learn":[0.8695626228],"iteration":124,"passed_time":0.9249606351,"remaining_time":0.5549763811},
{"learn":[0.8692580507],"iteration":125,"passed_time":0.9319980095,"remaining_time":0.5473639103},
{"learn":[0.8688346296],"iteration":126,"passed_time":0.9392782421,"remaining_time":0.5399000919},
{"learn":[0.8682326571],"iteration":127,"passed_time":0.9467793727,"remaining_time":0.5325633971},
{"learn":[0.8678035746],"iteration":128,"passed_time":0.9541258058,"remaining_time":0.5251390094},
{"learn":[0.8675555566],"iteration":129,"passed_time":0.9611148165,"remaining_time":0.5175233627},
{"learn":[0.8672119355],"iteration":130,"passed_time":0.9682849464,"remaining_time":0.5100126817},
{"learn":[0.8666228034],"iteration":131,"passed_time":0.9758462707,"remaining_time":0.5027086849},
{"learn":[0.8664765789],"iteration":132,"passed_time":0.9826187875,"remaining_time":0.4950034494},
{"learn":[0.866135743],"iteration":133,"passed_time":0.9898859956,"remaining_time":0.4875557889},
{"learn":[0.865277498],"iteration":134,"passed_time":0.9976160619,"remaining_time":0.4803336594},
{"learn":[0.865084503],"iteration":135,"passed_time":1.004696218,"remaining_time":0.47279822},
{"learn":[0.864621448],"iteration":136,"passed_time":1.012024724,"remaining_time":0.4653836321},
{"learn":[0.8644704339],"iteration":137,"passed_time":1.018837553,"remaining_time":0.4577386108},
{"learn":[0.8640952088],"iteration":138,"passed_time":1.025935272,"remaining_time":0.450230587},
{"learn":[0.8636249435],"iteration":139,"passed_time":1.033063984,"remaining_time":0.4427417075},
{"learn":[0.862837505],"iteration":140,"passed_time":1.04084366,"remaining_time":0.435530326},
{"learn":[0.8621269545],"iteration":141,"passed_time":1.048649355,"remaining_time":0.4283215674},
{"learn":[0.8614727757],"iteration":142,"passed_time":1.055943712,"remaining_time":0.4209006406},
{"learn":[0.86059157],"iteration":143,"passed_time":1.063551084,"remaining_time":0.4136031994},
{"learn":[0.8603792971],"iteration":144,"passed_time":1.07074607,"remaining_time":0.4061450609},
{"learn":[0.8601427808],"iteration":145,"passed_time":1.077711203,"remaining_time":0.3986055134},
{"learn":[0.8595417545],"iteration":146,"passed_time":1.085125253,"remaining_time":0.3912356354},
{"learn":[0.8591583282],"iteration":147,"passed_time":1.092117917,"remaining_time":0.3837171059},
{"learn":[0.8588791132],"iteration":148,"passed_time":1.099354887,"remaining_time":0.3762892567},
{"learn":[0.8583472377],"iteration":149,"passed_time":1.111951839,"remaining_time":0.370650613},
{"learn":[0.8578109553],"iteration":150,"passed_time":1.119345115,"remaining_time":0.3632311963},
{"learn":[0.8570241441],"iteration":151,"passed_time":1.126710681,"remaining_time":0.355803373},
{"learn":[0.8566188472],"iteration":152,"passed_time":1.133998198,"remaining_time":0.3483523876},
{"learn":[0.8562446984],"iteration":153,"passed_time":1.141151128,"remaining_time":0.340863324},
{"learn":[0.8555015047],"iteration":154,"passed_time":1.148798425,"remaining_time":0.3335221234},
{"learn":[0.8549884074],"iteration":155,"passed_time":1.155959349,"remaining_time":0.3260398165},
{"learn":[0.8547008575],"iteration":156,"passed_time":1.163235307,"remaining_time":0.3185931095},
{"learn":[0.8540032619],"iteration":157,"passed_time":1.171717801,"remaining_time":0.3114692889},
{"learn":[0.8534501431],"iteration":158,"passed_time":1.179726012,"remaining_time":0.3042060786},
{"learn":[0.8529805058],"iteration":159,"passed_time":1.188675617,"remaining_time":0.2971689043},
{"learn":[0.8527767934],"iteration":160,"passed_time":1.196149068,"remaining_time":0.2897503954},
{"learn":[0.8524207617],"iteration":161,"passed_time":1.203933653,"remaining_time":0.2824041902},
{"learn":[0.8518696897],"iteration":162,"passed_time":1.211853652,"remaining_time":0.2750833444},
{"learn":[0.8510840307],"iteration":163,"passed_time":1.219219386,"remaining_time":0.2676335237},
{"learn":[0.8505093309],"iteration":164,"passed_time":1.226884832,"remaining_time":0.2602482976},
{"learn":[0.8501247629],"iteration":165,"passed_time":1.234044337,"remaining_time":0.252756069},
{"learn":[0.8493550339],"iteration":166,"passed_time":1.241861918,"remaining_time":0.2453978641},
{"learn":[0.8486789018],"iteration":167,"passed_time":1.249140649,"remaining_time":0.2379315522},
{"learn":[0.848008823],"iteration":168,"passed_time":1.256608548,"remaining_time":0.2305021596},
{"learn":[0.8474881578],"iteration":169,"passed_time":1.263982444,"remaining_time":0.2230557255},
{"learn":[0.8470052456],"iteration":170,"passed_time":1.271539479,"remaining_time":0.2156411982},
{"learn":[0.8464302047],"iteration":171,"passed_time":1.280061725,"remaining_time":0.2083821413},
{"learn":[0.8459301367],"iteration":172,"passed_time":1.287364646,"remaining_time":0.2009181817},
{"learn":[0.845169531],"iteration":173,"passed_time":1.294734571,"remaining_time":0.1934660853},
{"learn":[0.8448713319],"iteration":174,"passed_time":1.301748688,"remaining_time":0.1859640983},
{"learn":[0.8443726461],"iteration":175,"passed_time":1.309305611,"remaining_time":0.1785416742},
{"learn":[0.8438988267],"iteration":176,"passed_time":1.316206431,"remaining_time":0.1710324741},
{"learn":[0.843246434],"iteration":177,"passed_time":1.323448961,"remaining_time":0.1635723435},
{"learn":[0.8427695647],"iteration":178,"passed_time":1.331328189,"remaining_time":0.1561893406},
{"learn":[0.8420765877],"iteration":179,"passed_time":1.338785943,"remaining_time":0.1487539937},
{"learn":[0.8416408857],"iteration":180,"passed_time":1.345770108,"remaining_time":0.1412686854},
{"learn":[0.8411126475],"iteration":181,"passed_time":1.35328989,"remaining_time":0.1338418572},
{"learn":[0.8408001875],"iteration":182,"passed_time":1.360539808,"remaining_time":0.126388944},
{"learn":[0.8403117784],"iteration":183,"passed_time":1.368004765,"remaining_time":0.1189569361},
{"learn":[0.8398804901],"iteration":184,"passed_time":1.375484876,"remaining_time":0.1115258007},
{"learn":[0.8394302398],"iteration":185,"passed_time":1.38289831,"remaining_time":0.1040891201},
{"learn":[0.8392041043],"iteration":186,"passed_time":1.389648786,"remaining_time":0.0966066001},
{"learn":[0.8388036571],"iteration":187,"passed_time":1.397192829,"remaining_time":0.08918252099},
{"learn":[0.838249493],"iteration":188,"passed_time":1.404567126,"remaining_time":0.08174729306},
{"learn":[0.838129455],"iteration":189,"passed_time":1.411283848,"remaining_time":0.07427809727},
{"learn":[0.8376737861],"iteration":190,"passed_time":1.418487736,"remaining_time":0.06683973627},
{"learn":[0.8372250857],"iteration":191,"passed_time":1.426101341,"remaining_time":0.05942088923},
{"learn":[0.8368376877],"iteration":192,"passed_time":1.433394687,"remaining_time":0.05198840832},
{"learn":[0.8359732998],"iteration":193,"passed_time":1.440938224,"remaining_time":0.04456509971},
{"learn":[0.8356215012],"iteration":194,"passed_time":1.448161149,"remaining_time":0.03713233716},
{"learn":[0.8352833553],"iteration":195,"passed_time":1.45538419,"remaining_time":0.02970171816},
{"learn":[0.8349956321],"iteration":196,"passed_time":1.462430762,"remaining_time":0.02227051922},
{"learn":[0.8345545118],"iteration":197,"passed_time":1.46989894,"remaining_time":0.01484746404},
{"learn":[0.8339878713],"iteration":198,"passed_time":1.47731762,"remaining_time":0.007423706635},
{"learn":[0.8334585127],"iteration":199,"passed_time":1.48460467,"remaining_time":0}
]}